paloalto_env/__init__.py
paloalto_env/paloalto_env.py
paloalto_env-0.1.7.dist-info/WHEEL
paloalto_env-0.1.7.dist-info/METADATA
paloalto_env-0.1.7.dist-info/RECORD
