Metadata-Version: 2.1
Name: paloalto-env
Version: 0.1.7
Summary: Palo Alto Env wrapper
Author: Thomas Christory
Requires-Python: >=3.8,<4.0
Classifier: Programming Language :: Python :: 3
Classifier: Programming Language :: Python :: 3.8
Classifier: Programming Language :: Python :: 3.9
Requires-Dist: python-dotenv (>=0.19.0)
